LICENSE
README.md
setup.py
container/__init__.py
container/container.py
universeparticle.egg-info/PKG-INFO
universeparticle.egg-info/SOURCES.txt
universeparticle.egg-info/dependency_links.txt
universeparticle.egg-info/not-zip-safe
universeparticle.egg-info/top_level.txt