Metadata-Version: 2.1
Name: universeparticle
Version: 0.1.0a1
Summary: common util
License-File: LICENSE
